vietvocoder/__init__.py
vietvocoder/loader.py
vietvocoder/predict.py
vietvocoder/stft.py
vietvocoder/train.py
vietvocoder/model/__init__.py
vietvocoder/model/denoiser.py
vietvocoder/model/layers.py
vietvocoder/model/predictor.py
vietvocoder/model/trainer.py
vietvocoder/model/waveglow.py
vietvocoder/utils/__init__.py
vietvocoder/utils/config.py
vietvocoder/utils/download_model.py
vietvocoder/utils/logger.py
vietvocoder-0.1.3.dist-info/METADATA
vietvocoder-0.1.3.dist-info/WHEEL
vietvocoder-0.1.3.dist-info/top_level.txt
vietvocoder-0.1.3.dist-info/RECORD
