Metadata-Version: 2.1
Name: vietvocoder
Version: 0.1.3
Summary: WaveGlow finetune for vietnamese voice
Home-page: https://github.com/pbcquoc/vietvocoder
Author: pbcquoc
Author-email: pbcquoc@gmail.com
License: UNKNOWN
Platform: UNKNOWN
Classifier: Programming Language :: Python :: 3
Classifier: License :: OSI Approved :: MIT License
Classifier: Operating System :: OS Independent
Requires-Python: >=3.6
Requires-Dist: gdown (==3.11.0)
